Metadata-Version: 2.1
Name: hyphaesque
Version: 0.0.1
Summary: An aesthetically conceptualised model for data processes and the interactions between various parts of data processing systems.
Home-page: https://github.com/MerfaSmean/hyphaesque
Author: Samuel Freeman
Author-email: soundmaking@merfasmean.com
License: MIT
Download-URL: https://github.com/MerfaSmean/hyphaesque/archive/refs/heads/main.zip
Platform: UNKNOWN
Classifier: Development Status :: 2 - Pre-Alpha
Classifier: Intended Audience :: Developers
Classifier: Topic :: Software Development
Classifier: License :: OSI Approved :: MIT License
Classifier: Operating System :: OS Independent
Classifier: Programming Language :: Python :: 3.7
